antievil/CHANGELOG.md
antievil/__init__.py
antievil/_expect.py
antievil/_main.py
antievil/test_expect.py
antievil/utils/__init__.py
antievil/utils/_info.py
antievil/utils/test_objectinfo.py
antievil-0.2.0.dist-info/LICENSE
antievil-0.2.0.dist-info/METADATA
antievil-0.2.0.dist-info/WHEEL
antievil-0.2.0.dist-info/RECORD
