Metadata-Version: 2.1
Name: antievil
Version: 0.2.0
Summary: Custom Errors for different programming languages.
License: MIT
Author: ryzhovalex
Author-email: thed4rkof@gmail.com
Requires-Python: >=3.11,<4.0
Classifier: License :: OSI Approved :: MIT License
Classifier: Programming Language :: Python :: 3
Classifier: Programming Language :: Python :: 3.11
